CHANGES.rst
COPYWRITE.txt
HISTORY.rst
LICENSE.txt
MANIFEST.in
README.rst
TWISTED-LICENSE
setup.py
src/zc/__init__.py
src/zc.zrs.egg-info/PKG-INFO
src/zc.zrs.egg-info/SOURCES.txt
src/zc.zrs.egg-info/dependency_links.txt
src/zc.zrs.egg-info/entry_points.txt
src/zc.zrs.egg-info/namespace_packages.txt
src/zc.zrs.egg-info/requires.txt
src/zc.zrs.egg-info/top_level.txt
src/zc.zrs.egg-info/zip-safe
src/zc/zrs/__init__.py
src/zc/zrs/component.xml
src/zc/zrs/config.test
src/zc/zrs/fsiterator.test
src/zc/zrs/last.py
src/zc/zrs/loopback.py
src/zc/zrs/monitor.py
src/zc/zrs/nagios.py
src/zc/zrs/nagios.rst
src/zc/zrs/primary-blob.test
src/zc/zrs/primary-blobstorage.test
src/zc/zrs/primary.py
src/zc/zrs/primary.test
src/zc/zrs/reactor.py
src/zc/zrs/secondary-blob.test
src/zc/zrs/secondary-blobstorage.test
src/zc/zrs/secondary.py
src/zc/zrs/secondary.test
src/zc/zrs/sizedmessage.py
src/zc/zrs/tests.py
src/zc/zrs/zconfig.py
src/zc/zrs/xformstorage/__init__.py
src/zc/zrs/xformstorage/component.xml