Metadata-Version: 1.1
Name: zc.zrs
Version: 3.0.0
Summary: ZODB Replicated Storage
Home-page: https://github.com/zc/zrs
Author: Jim Fulton
Author-email: jim@jimfulton.info
License: ZPL 2.1
Keywords: ZODB
Platform: UNKNOWN
Classifier: Intended Audience :: Developers
Classifier: License :: OSI Approved :: Zope Public License
Classifier: Programming Language :: Python
Classifier: Programming Language :: Python :: 2
Classifier: Programming Language :: Python :: 2.7
Classifier: Programming Language :: Python :: Implementation :: CPython
Classifier: Topic :: Database
Classifier: Topic :: Software Development :: Libraries :: Python Modules
Classifier: Operating System :: Microsoft :: Windows
Classifier: Operating System :: Unix
Classifier: Framework :: ZODB
